{
    "deciles": [
        2.5199,
        4.6207,
        5.8683,
        6.8277,
        7.8996,
        9.0902,
        10.568,
        12.61,
        15.662,
        24.333
    ],
    "dist": {
        "Gini": 0.326036,
        "median": {
            "lcu": 1075.97
        },
        "MLD": 0.20443
    },
    "poverty": {
        "Watt": 0.00112512,
        "HC": 0.00680959,
        "PG": 0.0181178,
        "line_month_ppp": 57.7917,
        "line_month_lcu": 30.6726,
        "line_day_ppp": 1.9,
        "FGT2": 0.0767864
    },
    "summary": {
        "mean_ppp": 1271.74,
        "ppp": 1.28458,
        "mean_lcu": 674.967
    },
    "pop": {
        "min": -82.4166,
        "max": 2767.09,
        "pop": 100.006,
        "N": 300,
        "wealth": 52546.8
    },
    "estimation": {
        "max_is_ppp": "(PPP$)",
        "wealth_is_ppp": "(PPP$)",
        "min_is_ppp": "(PPP$)"
    },
    "dataset": {
        "country": "Canada",
        "source": "CAN_N1981Y",
        "coverage": "National",
        "timespan": "UnDefined",
        "year": 1981,
        "format": "Unit record",
        "measure": "Income",
        "cc3": "CAN"
    },
    "distribution": {
        "L": [
            0.0084066,
            0.025207,
            0.04651,
            0.07142,
            0.099495,
            0.13029,
            0.1634,
            0.19837,
            0.23654,
            0.27751,
            0.32144,
            0.3683,
            0.42244,
            0.4743,
            0.53433,
            0.60005,
            0.679,
            0.75684,
            0.85535,
            1.0
        ],
        "index": [
            0,
            1,
            2,
            3,
            4,
            5,
            6,
            7,
            8,
            9,
            10,
            11,
            12,
            13,
            14,
            15,
            16,
            17,
            18,
            19
        ],
        "p": [
            0.050047,
            0.10002,
            0.15002,
            0.20003,
            0.25006,
            0.30033,
            0.35048,
            0.40001,
            0.45012,
            0.50018,
            0.55015,
            0.60003,
            0.65333,
            0.70032,
            0.75029,
            0.8,
            0.85341,
            0.90011,
            0.95004,
            1.0
        ]
    }
}