{
    "dist": {
        "Gini": 42.8884,
        "uses": "GQ",
        "mean_corrected_ppp": -0.0529849,
        "mean_poor50_ppp": 3.12701,
        "median_ppp": 4.98214,
        "polarization": 39.0918,
        "MLD": 0.305544,
        "uses_commentary": "(Both are valid and normal, but GQ fits better.)"
    },
    "deciles": [
        2.55789,
        3.38848,
        4.26849,
        5.23179,
        6.32812,
        7.63955,
        9.32081,
        11.7231,
        15.9501,
        33.5916
    ],
    "distribution": {
        "L": [
            0.01024707,
            0.0243534,
            0.04078551,
            0.05942101,
            0.0800698,
            0.1027809,
            0.1277455,
            0.1550708,
            0.1850297,
            0.2178171,
            0.253894,
            0.2937498,
            0.3378006,
            0.3867771,
            0.4416484,
            0.50426,
            0.5772988,
            0.6653868,
            0.779223,
            1.0
        ],
        "index": [
            1,
            2,
            3,
            4,
            5,
            6,
            7,
            8,
            9,
            10,
            11,
            12,
            13,
            14,
            15,
            16,
            17,
            18,
            19,
            20
        ],
        "p": [
            0.05,
            0.1,
            0.15,
            0.2,
            0.25,
            0.3,
            0.35,
            0.4,
            0.45,
            0.5,
            0.55,
            0.6,
            0.65,
            0.7,
            0.75,
            0.8,
            0.85,
            0.9,
            0.95,
            1.0
        ]
    },
    "elasticity": {
        "FGT2": {
            "meancons": -4.00282,
            "Gini": 10.0733
        },
        "HC": {
            "meancons": -1.86806,
            "Gini": 2.51239
        },
        "PG": {
            "Gini": 6.31915,
            "meancons": -2.955
        }
    },
    "dataset": {
        "format": "Grouped",
        "measure": "Consumption",
        "year": 1994,
        "source": "PHL_N1994X",
        "cc3": "PHL",
        "timespan": "UnDefined",
        "coverage": "National",
        "country": "Philippines"
    },
    "beta": {
        "dist": {
            "Gini": 42.9415,
            "mean_corrected_ppp": 4.097,
            "mean_poor50_ppp": 3.1185,
            "median_ppp": 5.09188,
            "polarization": -124.57,
            "MLD": 0.311811
        },
        "deciles": [
            2.45078,
            3.3146,
            4.23989,
            5.26845,
            6.44183,
            7.82663,
            9.54658,
            11.8774,
            15.6702,
            33.3636
        ],
        "implied": {
            "delta": 0.4828955,
            "theta": 0.7889674,
            "gamma": 0.9970609
        },
        "elasticity": {
            "FGT2": {
                "meancons": -3.66199,
                "Gini": 9.61491
            },
            "HC": {
                "Gini": 2.33045,
                "meancons": -1.73279
            },
            "PG": {
                "Gini": 6.00708,
                "meancons": -2.72296
            }
        },
        "poverty": {
            "Watt": 0.0846935,
            "FGT2": 2.40023,
            "HC": 25.2977,
            "PG": 6.79504,
            "line_month_ppp": 57.7917
        },
        "summary": {
            "normality": "Normal",
            "sse": {
                "tohc": 1.80136e-05,
                "fitted": 0.000169263
            },
            "mean_ppp": 135.517,
            "Z": {
                "high": 497.959,
                "low": 30.8315
            },
            "validity": "Valid"
        },
        "reg": {
            "ymean": -1.606304,
            "SSE": 0.003693467,
            "RMSE": 0.01519348,
            "SST": 5.544315,
            "R2": 0.9993338,
            "params": {
                "A": {
                    "coef": 0.482896,
                    "t": 67.5517,
                    "se": 0.0071485
                }
            },
            "MSE": 0.0002308417
        }
    },
    "poverty": {
        "Watt": 0.0813584,
        "FGT2": 2.10554,
        "HC": 24.994,
        "PG": 6.31959,
        "line_month_ppp": 57.7917
    },
    "summary": {
        "normality": "Normal",
        "sse": {
            "tohc": 4.44604e-06,
            "fitted": 9.66693e-06
        },
        "mean_ppp": 135.517,
        "Z": {
            "high": 561.606,
            "low": 33.2774
        },
        "validity": "Valid"
    },
    "quadratic": {
        "dist": {
            "Gini": 42.8884,
            "mean_corrected_ppp": 4.10081,
            "mean_poor50_ppp": 3.12701,
            "median_ppp": 4.98214,
            "polarization": 39.0918,
            "MLD": 0.305544
        },
        "deciles": [
            2.55789,
            3.38848,
            4.26849,
            5.23179,
            6.32812,
            7.63955,
            9.32081,
            11.7231,
            15.9501,
            33.5916
        ],
        "elasticity": {
            "FGT2": {
                "meancons": -4.00282,
                "Gini": 10.0733
            },
            "HC": {
                "Gini": 2.51239,
                "meancons": -1.86806
            },
            "PG": {
                "Gini": 6.31915,
                "meancons": -2.955
            }
        },
        "poverty": {
            "Watt": 0.0813584,
            "FGT2": 2.10554,
            "HC": 24.994,
            "PG": 6.31959,
            "line_month_ppp": 57.7917
        },
        "summary": {
            "normality": "Normal",
            "sse": {
                "tohc": 4.44604e-06,
                "fitted": 9.66693e-06
            },
            "mean_ppp": 135.517,
            "Z": {
                "high": 561.606,
                "low": 33.2774
            },
            "validity": "Valid"
        },
        "reg": {
            "ymean": 0.1500766,
            "SSE": 2.138203e-05,
            "RMSE": 0.001156018,
            "SST": 0.119896,
            "R2": 0.9998217,
            "params": {
                "B": {
                    "coef": -0.342111,
                    "t": -8.56551,
                    "se": 0.03994
                },
                "A": {
                    "coef": 0.749159,
                    "t": 115.666,
                    "se": 0.0064769
                },
                "C": {
                    "coef": 0.385912,
                    "t": 25.0605,
                    "se": 0.015399
                }
            },
            "MSE": 1.336377e-06
        }
    }
}